predixy/__init__.py
predixy/_version.py
predixy/additivity.py
predixy/aroma.py
predixy/config.ini
predixy/const.py
predixy/core.py
predixy/fragments.py
predixy/knot.py
predixy/knotidentifier.py
predixy/mol.py
predixy/molloader.py
predixy/path.py
predixy/pathfinder.py
predixy/plotting.py
predixy/scan_data.csv
predixy/utils.py
predixy-1.2.0.dist-info/LICENSE
predixy-1.2.0.dist-info/METADATA
predixy-1.2.0.dist-info/WHEEL
predixy-1.2.0.dist-info/entry_points.txt
predixy-1.2.0.dist-info/top_level.txt
predixy-1.2.0.dist-info/RECORD
