Metadata-Version: 2.1
Name: predixy
Version: 1.2.0
Summary: A command line program to predict NICS-XY scan results based on an additivity scheme.
Home-page: https://gitlab.com/porannegroup/predixy
Author: Poranne group
Author-email: renana.poranne@org.chem.ethz.ch
License: GNU GPLv3
Keywords: chemistry aromaticity PAH aroma
Platform: UNKNOWN
Classifier: Development Status :: 5 - Production/Stable
Requires-Python: >=3.7, <4
Requires-Dist: numpy (>=1.19.2)
Requires-Dist: scipy (>=1.5.2)
Requires-Dist: pandas (>=1.1.2)
Requires-Dist: tabulate (>=0.8.7)
Requires-Dist: matplotlib (>=3.3.2)
Requires-Dist: networkx (>=2.5)
